correlation.py
correlation-1.0.0.data/scripts/correlation.py
correlation-1.0.0.dist-info/LICENSE.txt
correlation-1.0.0.dist-info/METADATA
correlation-1.0.0.dist-info/WHEEL
correlation-1.0.0.dist-info/top_level.txt
correlation-1.0.0.dist-info/zip-safe
correlation-1.0.0.dist-info/RECORD
